simplexers/__init__.py
simplexers/capped.py
simplexers/positive.py
simplexers/core/arraytools.py
simplexers-1.0.0.dist-info/LICENSE
simplexers-1.0.0.dist-info/METADATA
simplexers-1.0.0.dist-info/WHEEL
simplexers-1.0.0.dist-info/top_level.txt
simplexers-1.0.0.dist-info/RECORD
