Metadata-Version: 2.1
Name: simplexers
Version: 1.0.0
Summary: Vector Projections onto Positive and Capped Simplices
Author-email: Matthew Caudill <mscaudill@gmail.com>
Project-URL: Homepage, https://github.com/mscaudill/simplexers
Keywords: machine learning,large-scale optimization
Classifier: Development Status :: 5 - Production/Stable
Classifier: Operating System :: POSIX :: Linux
Classifier: Programming Language :: Python
Classifier: License :: OSI Approved :: BSD License
Classifier: Topic :: Education
Classifier: Topic :: Software Development
Classifier: Topic :: Scientific/Engineering
Requires-Python: >=3.10
License-File: LICENSE
Requires-Dist: numpy
Requires-Dist: scipy
Provides-Extra: dev
Requires-Dist: ipython; extra == "dev"
Requires-Dist: notebook; extra == "dev"
Requires-Dist: isort; extra == "dev"
Requires-Dist: mypy; extra == "dev"
Requires-Dist: pylint; extra == "dev"
Requires-Dist: black; extra == "dev"
Requires-Dist: codespell; extra == "dev"
Requires-Dist: pytest==7.4.4; extra == "dev"
Requires-Dist: pytest-lazy-fixture; extra == "dev"
Requires-Dist: bumpver; extra == "dev"
Requires-Dist: pip-tools; extra == "dev"
Requires-Dist: build; extra == "dev"
Requires-Dist: twine; extra == "dev"
Provides-Extra: lint
Requires-Dist: pylint; extra == "lint"
Provides-Extra: test
Requires-Dist: pytest==7.4.4; extra == "test"
Requires-Dist: pytest-lazy-fixture; extra == "test"
